{
  "refreshedAt": "2026-07-11T12:00:16.592821",
  "prices": {
    "ILF": {
      "price": 34.5099983215332,
      "date": "2026-07-10",
      "time": null,
      "open": 34.189998626708984,
      "high": 34.599998474121094,
      "low": 34.189998626708984,
      "volume": 1826000.0,
      "source": "Yahoo Finance",
      "stale": false
    },
    "ARGT": {
      "price": 95.06999969482422,
      "date": "2026-07-10",
      "time": null,
      "open": 92.33999633789062,
      "high": 95.5,
      "low": 92.33999633789062,
      "volume": 112300.0,
      "source": "Yahoo Finance",
      "stale": false
    },
    "GLD": {
      "price": 377.010009765625,
      "date": "2026-07-10",
      "time": null,
      "open": 375.0,
      "high": 377.54998779296875,
      "low": 373.70001220703125,
      "volume": 5453000.0,
      "source": "Yahoo Finance",
      "stale": false
    },
    "IBIT": {
      "price": 36.22999954223633,
      "date": "2026-07-10",
      "time": null,
      "open": 36.32500076293945,
      "high": 36.65999984741211,
      "low": 36.08000183105469,
      "volume": 30663200.0,
      "source": "Yahoo Finance",
      "stale": false
    },
    "CSPX": {
      "price": 813.6699829101562,
      "date": "2026-07-10",
      "time": null,
      "open": 810.5700073242188,
      "high": 815.2382202148438,
      "low": 808.5,
      "volume": 113803.0,
      "source": "Yahoo Finance",
      "stale": false
    },
    "THOR": {
      "price": 37.9900016784668,
      "date": "2026-07-10",
      "time": null,
      "open": 37.9900016784668,
      "high": 37.9900016784668,
      "low": 37.9900016784668,
      "volume": 0,
      "source": "Yahoo Finance",
      "stale": false
    },
    "4BRZ": {
      "price": 35.93000030517578,
      "date": "2026-07-10",
      "time": null,
      "open": 35.599998474121094,
      "high": 35.9900016784668,
      "low": 35.560001373291016,
      "volume": 32969200.0,
      "source": "Yahoo Finance",
      "stale": false
    },
    "HLEND": null,
    "BPCC": null,
    "GCRED": null
  },
  "_meta": {
    "fresh": 7,
    "stale": 0,
    "guard_note": "Tickers con stale=true mantienen ultimo precio valido (yfinance retorno NaN)"
  }
}